FileHarvestor/__init__.py
FileHarvestor/src/FileHarvestor.py
FileHarvestor/src/__init__.py
FileHarvestor/test/__init__.py
FileHarvestor/test/file_maker.py
FileHarvestor/test/test_FileHarvestor.py
FileHarvestor-1.0.3.dist-info/LICENSE.txt
FileHarvestor-1.0.3.dist-info/METADATA
FileHarvestor-1.0.3.dist-info/WHEEL
FileHarvestor-1.0.3.dist-info/top_level.txt
FileHarvestor-1.0.3.dist-info/RECORD
