Metadata-Version: 2.1
Name: FileHarvestor
Version: 1.0.3
Summary: FileHarvestor is a Python utility that reads the contents of specified files and writes them to both text and markdown files. If a file does not exist, it is added to a list of not found files. This tool is useful for consolidating and documenting the contents of multiple files in a directory.
Home-page: https://github.com/Hardvan/FileHarvestor
Author: Hardik Pawar
Author-email: hardikpawarh@gmail.com
License: UNKNOWN
Keywords: file,harvestor,read,write,text,markdown,file-reader,read-file
Platform: UNKNOWN
Classifier: Programming Language :: Python :: 3
Classifier: License :: OSI Approved :: MIT License
Classifier: Operating System :: OS Independent
Requires-Python: >=3.6
License-File: LICENSE.txt
